ligdicash/__init__.py
ligdicash/decorators.py
ligdicash/defaults.py
ligdicash/errors.py
ligdicash/payin.py
ligdicash/payout.py
ligdicash/providers.py
ligdicash/responses.py
ligdicash/transaction.py
ligdicash/wiki.py
ligdicash-1.0.5.dist-info/METADATA
ligdicash-1.0.5.dist-info/WHEEL
ligdicash-1.0.5.dist-info/top_level.txt
ligdicash-1.0.5.dist-info/RECORD
