Metadata-Version: 2.1
Name: ligdicash
Version: 1.0.5
Summary: Une bibliothèque Python pour manipuler l'API de Ligdicash.
Home-page: https://developers.ligdicash.com
Author: LigdiCash
Author-email: info@ligdicash.com
License: MIT
Classifier: Programming Language :: Python :: 3
Classifier: License :: OSI Approved :: MIT License
Classifier: Operating System :: OS Independent
Requires-Python: >=3.0
Requires-Dist: requests
